tg_ip_lookup/__init__.py
tg_ip_lookup/process_csv.py
tg_ip_lookup/cloudlookup/__init__.py
tg_ip_lookup/cloudlookup/cloudlookup.py
tg_ip_lookup/cloudlookup/loadCloudProviderData.py
tg_ip_lookup-0.0.1.dist-info/LICENSE.md
tg_ip_lookup-0.0.1.dist-info/METADATA
tg_ip_lookup-0.0.1.dist-info/WHEEL
tg_ip_lookup-0.0.1.dist-info/top_level.txt
tg_ip_lookup-0.0.1.dist-info/RECORD
