Metadata-Version: 2.1
Name: tg_ip_lookup
Version: 0.0.1
Summary: Find out which public cloud an IP address originates from.
Home-page: https://github.com/Twingate-Labs/tg-ip-lookup
Author: Twingate Labs
Author-email: labs@twingate.com
Project-URL: Bug Tracker, https://github.com/Twingate-Labs/tg-ip-lookup/issues
Classifier: Programming Language :: Python :: 3
Classifier: License :: OSI Approved :: Apache Software License
Classifier: Operating System :: OS Independent
Requires-Python: >=3.6
License-File: LICENSE.md
